{
  "activeFiles": [
    "src\\index.js",
    "src\\App.js",
    "src\\HomePage.js",
    "src\\contexts\\VersionStateContext.js",
    "src\\CustomizableImage.js",
    "src\\CustomizableTable.js",
    "src\\useFormValues.js",
    "src\\components\\extended_scaling\\ExtendedScaling.js",
    "src\\components\\extended_scaling\\ScalingSummary.js",
    "src\\components\\extended_scaling\\Card.js",
    "src\\styles\\HomePage.CSS\\HomePage4.css",
    "src\\FactEngine.js",
    "src\\styles\\HomePage.CSS\\HomePage_FactEngine.css",
    "src\\FactEngineAdmin.js",
    "src\\styles\\HomePage.CSS\\HomePage_FactAdmin.css",
    "src\\GeneralFormConfig.js",
    "src\\Popup.js",
    "src\\styles\\HomePage.CSS\\Popup.css",
    "src\\components\\modules\\SensitivitySelector.js",
    "src\\styles\\HomePage.CSS\\SensitivitySelector.css",
    "src\\styles\\HomePage.CSS\\HomePage1.css",
    "src\\styles\\HomePage.CSS\\HomePage2.css",
    "src\\styles\\HomePage.CSS\\HomePage3.css",
    "src\\styles\\HomePage.CSS\\HomePage5.css",
    "src\\styles\\HomePage.CSS\\HomePage6.css",
    "src\\styles\\HomePage.CSS\\HomePage_AboutUs.css",
    "src\\styles\\HomePage.CSS\\HomePage_buttons.css",
    "src\\styles\\HomePage.CSS\\HomePage_monitoring.css",
    "src\\styles\\HomePage.CSS\\HomePage_selectors.css",
    "src\\styles\\HomePage.CSS\\HomePage_neumorphic-tabs.css",
    "src\\styles\\Themes\\dark-theme.css",
    "src\\styles\\Themes\\normal-theme.css",
    "src\\styles\\Themes\\creative-theme.css",
    "src\\PropertySelector.js",
    "src\\MultiVersionSelector.js",
    "src\\VersionSelector.js",
    "src\\styles\\HomePage.CSS\\VersionSelector.css",
    "src\\Naturalmotion.js",
    "src\\styles\\HomePage.CSS\\Naturalmotion.css",
    "src\\components\\modules\\TestingZone.js",
    "src\\styles\\HomePage.CSS\\TestingZone.css",
    "src\\components\\cfa\\CFAConsolidationUI.js",
    "src\\components\\cfa\\CFAConsolidationUI.css",
    "src\\components\\cfa\\SelectionPanel.js",
    "src\\components\\cfa\\SelectionPanel.css",
    "src\\components\\cfa\\ProcessingPanel.js",
    "src\\components\\cfa\\ProcessingPanel.css",
    "src\\components\\cfa\\ResultsPanel.js",
    "src\\components\\cfa\\ResultsPanel.css",
    "src\\components\\cfa\\IndividualResultsPanel.js",
    "src\\components\\modules\\CalculationMonitor.js",
    "src\\styles\\HomePage.CSS\\CalculationMonitor.css",
    "src\\components\\modules\\SensitivityMonitor.js",
    "src\\styles\\HomePage.CSS\\SensitivityMonitor.css",
    "src\\components\\modules\\ConfigurationMonitor.js",
    "src\\styles\\HomePage.CSS\\ConfigurationMonitor.css",
    "src\\components\\modules\\ThemeButton.js",
    "src\\components\\modules\\ThemeConfigurator.js",
    "src\\utils\\ThemeGenerator.js",
    "src\\styles\\HomePage.CSS\\ThemeConfigurator.css",
    "src\\styles\\HomePage.CSS\\ThemeButton.css",
    "src\\components\\modules\\ErrorBoundary.js"
  ],
  "inactiveFiles": [
    "src\\components\\version\\VersionControl.css",
    "src\\components\\version\\VersionControl.js"
  ],
  "standaloneFiles": [
    "src\\contexts\\VersionStateContext.js",
    "src\\CustomizableImage.js",
    "src\\useFormValues.js",
    "src\\styles\\HomePage.CSS\\HomePage4.css",
    "src\\styles\\HomePage.CSS\\HomePage_FactEngine.css",
    "src\\styles\\HomePage.CSS\\HomePage_FactAdmin.css",
    "src\\styles\\HomePage.CSS\\Popup.css",
    "src\\styles\\HomePage.CSS\\SensitivitySelector.css",
    "src\\styles\\HomePage.CSS\\HomePage1.css",
    "src\\styles\\HomePage.CSS\\HomePage2.css",
    "src\\styles\\HomePage.CSS\\HomePage3.css",
    "src\\styles\\HomePage.CSS\\HomePage5.css",
    "src\\styles\\HomePage.CSS\\HomePage6.css",
    "src\\styles\\HomePage.CSS\\HomePage_AboutUs.css",
    "src\\styles\\HomePage.CSS\\HomePage_buttons.css",
    "src\\styles\\HomePage.CSS\\HomePage_monitoring.css",
    "src\\styles\\HomePage.CSS\\HomePage_selectors.css",
    "src\\styles\\HomePage.CSS\\HomePage_neumorphic-tabs.css",
    "src\\styles\\Themes\\dark-theme.css",
    "src\\styles\\Themes\\normal-theme.css",
    "src\\styles\\Themes\\creative-theme.css",
    "src\\styles\\HomePage.CSS\\VersionSelector.css",
    "src\\styles\\HomePage.CSS\\Naturalmotion.css",
    "src\\styles\\HomePage.CSS\\TestingZone.css",
    "src\\components\\cfa\\CFAConsolidationUI.css",
    "src\\components\\cfa\\SelectionPanel.css",
    "src\\components\\cfa\\ProcessingPanel.css",
    "src\\components\\cfa\\ResultsPanel.css",
    "src\\styles\\HomePage.CSS\\CalculationMonitor.css",
    "src\\styles\\HomePage.CSS\\SensitivityMonitor.css",
    "src\\styles\\HomePage.CSS\\ConfigurationMonitor.css",
    "src\\utils\\ThemeGenerator.js",
    "src\\styles\\HomePage.CSS\\ThemeConfigurator.css",
    "src\\styles\\HomePage.CSS\\ThemeButton.css",
    "src\\components\\modules\\ErrorBoundary.js"
  ],
  "dependencyLayers": {
    "0": [
      "src\\index.js"
    ],
    "1": [
      "src\\App.js"
    ],
    "2": [
      "src\\HomePage.js",
      "src\\contexts\\VersionStateContext.js",
      "src\\components\\modules\\ErrorBoundary.js"
    ],
    "3": [
      "src\\CustomizableImage.js",
      "src\\CustomizableTable.js",
      "src\\useFormValues.js",
      "src\\components\\extended_scaling\\ExtendedScaling.js",
      "src\\styles\\HomePage.CSS\\HomePage4.css",
      "src\\FactEngine.js",
      "src\\styles\\HomePage.CSS\\HomePage_FactEngine.css",
      "src\\FactEngineAdmin.js",
      "src\\styles\\HomePage.CSS\\HomePage_FactAdmin.css",
      "src\\GeneralFormConfig.js",
      "src\\styles\\HomePage.CSS\\HomePage1.css",
      "src\\styles\\HomePage.CSS\\HomePage2.css",
      "src\\styles\\HomePage.CSS\\HomePage3.css",
      "src\\styles\\HomePage.CSS\\HomePage5.css",
      "src\\styles\\HomePage.CSS\\HomePage6.css",
      "src\\styles\\HomePage.CSS\\HomePage_AboutUs.css",
      "src\\styles\\HomePage.CSS\\HomePage_buttons.css",
      "src\\styles\\HomePage.CSS\\HomePage_monitoring.css",
      "src\\styles\\HomePage.CSS\\HomePage_selectors.css",
      "src\\styles\\HomePage.CSS\\HomePage_neumorphic-tabs.css",
      "src\\styles\\Themes\\dark-theme.css",
      "src\\styles\\Themes\\normal-theme.css",
      "src\\styles\\Themes\\creative-theme.css",
      "src\\PropertySelector.js",
      "src\\MultiVersionSelector.js",
      "src\\VersionSelector.js",
      "src\\Naturalmotion.js",
      "src\\components\\modules\\TestingZone.js",
      "src\\components\\modules\\CalculationMonitor.js",
      "src\\components\\modules\\SensitivityMonitor.js",
      "src\\components\\modules\\ConfigurationMonitor.js",
      "src\\components\\modules\\ThemeButton.js"
    ],
    "4": [
      "src\\components\\extended_scaling\\ScalingSummary.js",
      "src\\Popup.js",
      "src\\components\\modules\\SensitivitySelector.js",
      "src\\styles\\HomePage.CSS\\VersionSelector.css",
      "src\\styles\\HomePage.CSS\\Naturalmotion.css",
      "src\\styles\\HomePage.CSS\\TestingZone.css",
      "src\\components\\cfa\\CFAConsolidationUI.js",
      "src\\styles\\HomePage.CSS\\CalculationMonitor.css",
      "src\\styles\\HomePage.CSS\\SensitivityMonitor.css",
      "src\\styles\\HomePage.CSS\\ConfigurationMonitor.css",
      "src\\components\\modules\\ThemeConfigurator.js",
      "src\\styles\\HomePage.CSS\\ThemeButton.css"
    ],
    "5": [
      "src\\components\\extended_scaling\\Card.js",
      "src\\styles\\HomePage.CSS\\Popup.css",
      "src\\styles\\HomePage.CSS\\SensitivitySelector.css",
      "src\\components\\cfa\\CFAConsolidationUI.css",
      "src\\components\\cfa\\SelectionPanel.js",
      "src\\components\\cfa\\ProcessingPanel.js",
      "src\\components\\cfa\\ResultsPanel.js",
      "src\\components\\cfa\\IndividualResultsPanel.js",
      "src\\utils\\ThemeGenerator.js",
      "src\\styles\\HomePage.CSS\\ThemeConfigurator.css"
    ],
    "6": [
      "src\\components\\cfa\\SelectionPanel.css",
      "src\\components\\cfa\\ProcessingPanel.css",
      "src\\components\\cfa\\ResultsPanel.css"
    ]
  },
  "importedBy": {
    "src\\App.js": [
      "src\\index.js"
    ],
    "src\\HomePage.js": [
      "src\\App.js"
    ],
    "src\\contexts\\VersionStateContext.js": [
      "src\\HomePage.js",
      "src\\MultiVersionSelector.js",
      "src\\VersionSelector.js",
      "src\\App.js"
    ],
    "src\\CustomizableImage.js": [
      "src\\HomePage.js"
    ],
    "src\\CustomizableTable.js": [
      "src\\HomePage.js",
      "src\\components\\cfa\\IndividualResultsPanel.js"
    ],
    "src\\useFormValues.js": [
      "src\\CustomizableTable.js",
      "src\\GeneralFormConfig.js",
      "src\\PropertySelector.js",
      "src\\HomePage.js"
    ],
    "src\\components\\extended_scaling\\ExtendedScaling.js": [
      "src\\HomePage.js"
    ],
    "src\\components\\extended_scaling\\ScalingSummary.js": [
      "src\\components\\extended_scaling\\ExtendedScaling.js"
    ],
    "src\\components\\extended_scaling\\Card.js": [
      "src\\components\\extended_scaling\\ScalingSummary.js"
    ],
    "src\\styles\\HomePage.CSS\\HomePage4.css": [
      "src\\components\\extended_scaling\\Card.js",
      "src\\components\\extended_scaling\\ExtendedScaling.js",
      "src\\HomePage.js"
    ],
    "src\\FactEngine.js": [
      "src\\HomePage.js"
    ],
    "src\\styles\\HomePage.CSS\\HomePage_FactEngine.css": [
      "src\\FactEngine.js",
      "src\\HomePage.js"
    ],
    "src\\FactEngineAdmin.js": [
      "src\\HomePage.js"
    ],
    "src\\styles\\HomePage.CSS\\HomePage_FactAdmin.css": [
      "src\\FactEngineAdmin.js",
      "src\\HomePage.js"
    ],
    "src\\GeneralFormConfig.js": [
      "src\\HomePage.js"
    ],
    "src\\Popup.js": [
      "src\\GeneralFormConfig.js"
    ],
    "src\\styles\\HomePage.CSS\\Popup.css": [
      "src\\Popup.js"
    ],
    "src\\components\\modules\\SensitivitySelector.js": [
      "src\\GeneralFormConfig.js"
    ],
    "src\\styles\\HomePage.CSS\\SensitivitySelector.css": [
      "src\\components\\modules\\SensitivitySelector.js"
    ],
    "src\\styles\\HomePage.CSS\\HomePage1.css": [
      "src\\HomePage.js"
    ],
    "src\\styles\\HomePage.CSS\\HomePage2.css": [
      "src\\HomePage.js"
    ],
    "src\\styles\\HomePage.CSS\\HomePage3.css": [
      "src\\HomePage.js"
    ],
    "src\\styles\\HomePage.CSS\\HomePage5.css": [
      "src\\HomePage.js"
    ],
    "src\\styles\\HomePage.CSS\\HomePage6.css": [
      "src\\HomePage.js"
    ],
    "src\\styles\\HomePage.CSS\\HomePage_AboutUs.css": [
      "src\\HomePage.js"
    ],
    "src\\styles\\HomePage.CSS\\HomePage_buttons.css": [
      "src\\HomePage.js"
    ],
    "src\\styles\\HomePage.CSS\\HomePage_monitoring.css": [
      "src\\HomePage.js"
    ],
    "src\\styles\\HomePage.CSS\\HomePage_selectors.css": [
      "src\\HomePage.js"
    ],
    "src\\styles\\HomePage.CSS\\HomePage_neumorphic-tabs.css": [
      "src\\HomePage.js"
    ],
    "src\\styles\\Themes\\dark-theme.css": [
      "src\\HomePage.js"
    ],
    "src\\styles\\Themes\\normal-theme.css": [
      "src\\HomePage.js"
    ],
    "src\\styles\\Themes\\creative-theme.css": [
      "src\\HomePage.js"
    ],
    "src\\PropertySelector.js": [
      "src\\HomePage.js"
    ],
    "src\\MultiVersionSelector.js": [
      "src\\HomePage.js"
    ],
    "src\\VersionSelector.js": [
      "src\\HomePage.js"
    ],
    "src\\styles\\HomePage.CSS\\VersionSelector.css": [
      "src\\VersionSelector.js"
    ],
    "src\\Naturalmotion.js": [
      "src\\HomePage.js"
    ],
    "src\\styles\\HomePage.CSS\\Naturalmotion.css": [
      "src\\Naturalmotion.js"
    ],
    "src\\components\\modules\\TestingZone.js": [
      "src\\HomePage.js"
    ],
    "src\\styles\\HomePage.CSS\\TestingZone.css": [
      "src\\components\\modules\\TestingZone.js"
    ],
    "src\\components\\cfa\\CFAConsolidationUI.js": [
      "src\\components\\modules\\TestingZone.js"
    ],
    "src\\components\\cfa\\CFAConsolidationUI.css": [
      "src\\components\\cfa\\CFAConsolidationUI.js"
    ],
    "src\\components\\cfa\\SelectionPanel.js": [
      "src\\components\\cfa\\CFAConsolidationUI.js"
    ],
    "src\\components\\cfa\\SelectionPanel.css": [
      "src\\components\\cfa\\SelectionPanel.js"
    ],
    "src\\components\\cfa\\ProcessingPanel.js": [
      "src\\components\\cfa\\CFAConsolidationUI.js"
    ],
    "src\\components\\cfa\\ProcessingPanel.css": [
      "src\\components\\cfa\\ProcessingPanel.js"
    ],
    "src\\components\\cfa\\ResultsPanel.js": [
      "src\\components\\cfa\\CFAConsolidationUI.js"
    ],
    "src\\components\\cfa\\ResultsPanel.css": [
      "src\\components\\cfa\\ResultsPanel.js",
      "src\\components\\cfa\\IndividualResultsPanel.js"
    ],
    "src\\components\\cfa\\IndividualResultsPanel.js": [
      "src\\components\\cfa\\CFAConsolidationUI.js"
    ],
    "src\\components\\modules\\CalculationMonitor.js": [
      "src\\HomePage.js"
    ],
    "src\\styles\\HomePage.CSS\\CalculationMonitor.css": [
      "src\\components\\modules\\CalculationMonitor.js"
    ],
    "src\\components\\modules\\SensitivityMonitor.js": [
      "src\\HomePage.js"
    ],
    "src\\styles\\HomePage.CSS\\SensitivityMonitor.css": [
      "src\\components\\modules\\SensitivityMonitor.js"
    ],
    "src\\components\\modules\\ConfigurationMonitor.js": [
      "src\\HomePage.js"
    ],
    "src\\styles\\HomePage.CSS\\ConfigurationMonitor.css": [
      "src\\components\\modules\\ConfigurationMonitor.js"
    ],
    "src\\components\\modules\\ThemeButton.js": [
      "src\\HomePage.js"
    ],
    "src\\components\\modules\\ThemeConfigurator.js": [
      "src\\components\\modules\\ThemeButton.js"
    ],
    "src\\utils\\ThemeGenerator.js": [
      "src\\components\\modules\\ThemeConfigurator.js"
    ],
    "src\\styles\\HomePage.CSS\\ThemeConfigurator.css": [
      "src\\components\\modules\\ThemeConfigurator.js"
    ],
    "src\\styles\\HomePage.CSS\\ThemeButton.css": [
      "src\\components\\modules\\ThemeButton.js"
    ],
    "src\\components\\modules\\ErrorBoundary.js": [
      "src\\App.js"
    ]
  }
}